atap_widgets/__init__.py
atap_widgets/concordance.py
atap_widgets/conversation.py
atap_widgets/plotting.py
atap_widgets/utils.py
atap_widgets-0.5.4.dist-info/LICENSE.rst
atap_widgets-0.5.4.dist-info/METADATA
atap_widgets-0.5.4.dist-info/WHEEL
atap_widgets-0.5.4.dist-info/RECORD
