Metadata-Version: 2.1
Name: atap_widgets
Version: 0.5.4
Summary: Interactive widgets used by the Australian Text Analytics Platform
Home-page: https://github.com/Australian-Text-Analytics-Platform/atap_widgets
License: MIT
Author: Marius Mather
Author-email: marius.mather@sydney.edu.au
Requires-Python: >=3.8,<=3.11
Classifier: Development Status :: 4 - Beta
Classifier: License :: OSI Approved :: MIT License
Classifier: Programming Language :: Python :: 3
Classifier: Programming Language :: Python :: 3.8
Classifier: Programming Language :: Python :: 3.9
Classifier: Programming Language :: Python :: 3.10
Classifier: Programming Language :: Python :: 3.11
Requires-Dist: bokeh (>=2.0,<3.0)
Requires-Dist: dask[dataframe] (>=2022.9.2,<2023.0.0)
Requires-Dist: ipywidgets (>=8.0,<9.0)
Requires-Dist: openpyxl
Requires-Dist: pandas (>=1.3,<2.0)
Requires-Dist: spacy (>=3.0,<4.0)
Requires-Dist: textacy
Requires-Dist: xlsxwriter (>=3,<4)
Project-URL: Changelog, https://github.com/Australian-Text-Analytics-Platform/atap_widgets/releases
Project-URL: Documentation, https://atap_widgets.readthedocs.io
Project-URL: Project homepage, https://www.atap.edu.au/
Project-URL: Repository, https://github.com/Australian-Text-Analytics-Platform/atap_widgets
